pyrepscan-0.12.0.dist-info/METADATA
pyrepscan-0.12.0.dist-info/WHEEL
pyrepscan-0.12.0.dist-info/license_files/LICENSE
pyrepscan/__init__.py
pyrepscan/py.typed
pyrepscan/pyrepscan.pyi
pyrepscan/pyrepscan.cpython-311-darwin.so
pyrepscan-0.12.0.dist-info/RECORD
