Metadata-Version: 2.1
Name: pyrepscan
Version: 0.12.0
Classifier: License :: OSI Approved :: MIT License
Classifier: Operating System :: MacOS
Classifier: Operating System :: Microsoft
Classifier: Operating System :: POSIX :: Linux
Classifier: Programming Language :: Python :: 3.7
Classifier: Programming Language :: Python :: 3.8
Classifier: Programming Language :: Python :: 3.9
Classifier: Programming Language :: Python :: 3.10
Classifier: Programming Language :: Python :: 3.11
Classifier: Programming Language :: Rust
License-File: LICENSE
Summary: A Git Repository Secrets Scanner written in Rust
Keywords: git,secrets,scanner,rust,pyo3
Home-Page: https://github.com/intsights/pyrepscan
Author: Gal Ben David
Author-email: gal@intsights.com
License: MIT
Requires-Python: >=3.7
Project-URL: Source Code, https://github.com/intsights/pyrepscan
